<?xml version="1.0" encoding="UTF-8"?>
<!--
/********************************************************************
*  Licensed Materials - Property of IBM
*  
*  (c) Copyright IBM Corp.  2007, 2009 All Rights Reserved
*  
*  US Government Users Restricted Rights - Use, duplication or
*  disclosure restricted by GSA ADP Schedule Contract with
*  IBM Corp.
********************************************************************/
-->
<MetamergeConfig created="Fri Mar 28 10:20:21 CST 2003" createdBy="sam" modified="Fri May 23 14:16:55 CDT 2003" modifiedBy="sam" version="1.0">
<Folder name="AssemblyLines">
<AssemblyLine name="LDAPMDImport">
<Settings>
<parameter name="automapattributes">false</parameter>
<parameter name="debug">false</parameter>
<parameter name="includeGlobalPrologs">true</parameter>
<parameter name="nullBehavior">Default Behavior</parameter>
</Settings>
<IOSettings>
<InputParameters/>
<OutputParameters/>
</IOSettings>
<Connectors>
<Connector name="FindMDLDAPTAMusers">
<InheritFrom>/Connectors/FindMDLDAPTAMusers</InheritFrom>
<ConnectorMode>Iterator</ConnectorMode>
<ConnectorState>Enabled</ConnectorState>
<Configuration>
<InheritFrom>[parent]</InheritFrom>
<parameter name="ldapPassword">@PROPERTY{TAM_LDAP_PW}</parameter>
<parameter name="ldapUrl">@PROPERTY{TAM_LDAP_URL}</parameter>
<parameter name="ldapUsername">@PROPERTY{TAM_LDAP_Login}</parameter>
</Configuration>
<Parser>
<InheritFrom>[parent]</InheritFrom>
</Parser>
<AttributeMap name="Input">
<InheritFrom>[parent]</InheritFrom>
<AttributeMapItem>
<Name>secdn</Name>
<Type>simple</Type>
<Add>true</Add>
<Modify>true</Modify>
<Script/>
<Simple>secdn</Simple>
</AttributeMapItem>
</AttributeMap>
<AttributeMap name="Output">
<InheritFrom>[parent]</InheritFrom>
</AttributeMap>
<DeltaSettings/>
<Schema>
<InheritFrom>[parent]</InheritFrom>
<SchemaItem>
<Name>$dn</Name>
<Syntax>java.lang.String</Syntax>
<DefaultValue>null</DefaultValue>
<Syntax>java.lang.String</Syntax>
<RequiredInput>false</RequiredInput>
<RequiredOutput>false</RequiredOutput>
<Excluded>false</Excluded>
</SchemaItem>
<SchemaItem>
<Name>objectClass</Name>
<NativeSyntax>MUST/OID/The values of the objectClass attribute describe the kind of object which an entry represents.</NativeSyntax>
<DefaultValue>null</DefaultValue>
<RequiredInput>false</RequiredInput>
<RequiredOutput>false</RequiredOutput>
<Excluded>false</Excluded>
</SchemaItem>
<SchemaItem>
<Name>objectclass</Name>
<Syntax>java.lang.String</Syntax>
<DefaultValue>null</DefaultValue>
<Syntax>java.lang.String</Syntax>
<RequiredInput>false</RequiredInput>
<RequiredOutput>false</RequiredOutput>
<Excluded>false</Excluded>
</SchemaItem>
<SchemaItem>
<Name>secDN</Name>
<NativeSyntax>MUST/DN/DN of an ePerson or accessGroup</NativeSyntax>
<DefaultValue>null</DefaultValue>
<RequiredInput>false</RequiredInput>
<RequiredOutput>false</RequiredOutput>
<Excluded>false</Excluded>
</SchemaItem>
<SchemaItem>
<Name>secUUID</Name>
<NativeSyntax>MUST/IA5 String{37}/Policy Director universally unique ID, string as per DCE (E.G. 2495d190-be07-11d1-82ed-00c078500253)</NativeSyntax>
<DefaultValue>null</DefaultValue>
<RequiredInput>false</RequiredInput>
<RequiredOutput>false</RequiredOutput>
<Excluded>false</Excluded>
</SchemaItem>
<SchemaItem>
<Name>secdn</Name>
<Syntax>java.lang.String</Syntax>
<DefaultValue>null</DefaultValue>
<Syntax>java.lang.String</Syntax>
<RequiredInput>false</RequiredInput>
<RequiredOutput>false</RequiredOutput>
<Excluded>false</Excluded>
</SchemaItem>
<SchemaItem>
<Name>secuuid</Name>
<Syntax>java.lang.String</Syntax>
<DefaultValue>null</DefaultValue>
<Syntax>java.lang.String</Syntax>
<RequiredInput>false</RequiredInput>
<RequiredOutput>false</RequiredOutput>
<Excluded>false</Excluded>
</SchemaItem>
</Schema>
<LinkCriteria>
<InheritFrom>[parent]</InheritFrom>
<AdvancedLinkMode>false</AdvancedLinkMode>
</LinkCriteria>
<Hooks>
<InheritFrom>[parent]</InheritFrom>
<Hook>
<Name>after_getnext</Name>
<Script><![CDATA[var tdn=conn.getString("$dn");
var sdn=conn.getString("secdn");
if ((tdn.indexOf("cn=Users",0) <= 0) ||
           (sdn.indexOf("SecurityMaster",0) > 0))
   system.skipEntry();
else
   task.logmsg("---> TAM user is found." + sdn);]]></Script>
<Enabled>true</Enabled>
<DebugBreak>false</DebugBreak>
</Hook>
</Hooks>
</Connector>
<Connector name="GetMDLDAPTAMUsers">
<InheritFrom>/Connectors/GetMDLDAPTAMUsers</InheritFrom>
<ConnectorMode>Lookup</ConnectorMode>
<ConnectorState>Enabled</ConnectorState>
<Configuration>
<InheritFrom>[parent]</InheritFrom>
<parameter name="ldapPassword">@PROPERTY{TAM_LDAP_PW}</parameter>
<parameter name="ldapSearchBase">ou=tivoli</parameter>
<parameter name="ldapUrl">@PROPERTY{TAM_LDAP_URL}</parameter>
<parameter name="ldapUsername">@PROPERTY{TAM_LDAP_Login}</parameter>
</Configuration>
<Parser>
<InheritFrom>[parent]</InheritFrom>
</Parser>
<AttributeMap name="Input">
<InheritFrom>[parent]</InheritFrom>
<AttributeMapItem>
<Name>uid</Name>
<Type>simple</Type>
<Add>true</Add>
<Modify>true</Modify>
<Script/>
<Simple>uid</Simple>
</AttributeMapItem>
</AttributeMap>
<AttributeMap name="Output">
<InheritFrom>[parent]</InheritFrom>
</AttributeMap>
<DeltaSettings/>
<Schema>
<InheritFrom>[parent]</InheritFrom>
<SchemaItem>
<Name>$dn</Name>
<Syntax>java.lang.String</Syntax>
<DefaultValue>null</DefaultValue>
<Syntax>java.lang.String</Syntax>
<RequiredInput>false</RequiredInput>
<RequiredOutput>false</RequiredOutput>
<Excluded>false</Excluded>
</SchemaItem>
<SchemaItem>
<Name>cn</Name>
<Syntax>java.lang.String</Syntax>
<NativeSyntax>MUST/String/This is the X.500 commonName attribute, which contains a name of an object.  If the object corresponds to a person, it is typically the persons full name.</NativeSyntax>
<DefaultValue>null</DefaultValue>
<Syntax>java.lang.String</Syntax>
<RequiredInput>false</RequiredInput>
<RequiredOutput>false</RequiredOutput>
<Excluded>false</Excluded>
</SchemaItem>
<SchemaItem>
<Name>objectclass</Name>
<Syntax>java.lang.String</Syntax>
<DefaultValue>null</DefaultValue>
<Syntax>java.lang.String</Syntax>
<RequiredInput>false</RequiredInput>
<RequiredOutput>false</RequiredOutput>
<Excluded>false</Excluded>
</SchemaItem>
<SchemaItem>
<Name>sn</Name>
<Syntax>java.lang.String</Syntax>
<NativeSyntax>MUST/String/This is the X.500 surname attribute, which contains the family name of a person.</NativeSyntax>
<DefaultValue>null</DefaultValue>
<Syntax>java.lang.String</Syntax>
<RequiredInput>false</RequiredInput>
<RequiredOutput>false</RequiredOutput>
<Excluded>false</Excluded>
</SchemaItem>
<SchemaItem>
<Name>uid</Name>
<Syntax>java.lang.String</Syntax>
<NativeSyntax>MAY/Directory String/Typically a user shortname or userid.</NativeSyntax>
<DefaultValue>null</DefaultValue>
<Syntax>java.lang.String</Syntax>
<RequiredInput>false</RequiredInput>
<RequiredOutput>false</RequiredOutput>
<Excluded>false</Excluded>
</SchemaItem>
<SchemaItem>
<Name>userpassword</Name>
<Syntax>[byte array]</Syntax>
<DefaultValue>null</DefaultValue>
<Syntax>[byte array]</Syntax>
<RequiredInput>false</RequiredInput>
<RequiredOutput>false</RequiredOutput>
<Excluded>false</Excluded>
</SchemaItem>
</Schema>
<LinkCriteria>
<InheritFrom>[parent]</InheritFrom>
<AdvancedLinkMode>false</AdvancedLinkMode>
<LinkCriteriaItem>
<Key>f431dca2bf</Key>
<Attribute>$dn</Attribute>
<Operator>equals</Operator>
<Value>$secdn</Value>
</LinkCriteriaItem>
</LinkCriteria>
<Hooks>
<InheritFrom>[parent]</InheritFrom>
</Hooks>
</Connector>
<Connector name="TIMImport">
<InheritFrom>/Connectors/TIMImport</InheritFrom>
<ConnectorMode>AddOnly</ConnectorMode>
<ConnectorState>Enabled</ConnectorState>
<Configuration>
<InheritFrom>[parent]</InheritFrom>
<parameter name="java.naming.provider.url">@PROPERTY{TIM_DSMLv2_URL}</parameter>
<parameter name="java.naming.security.credentials">@PROPERTY{TIM_DSMLv2_PW}</parameter>
<parameter name="java.naming.security.principal">@PROPERTY{TIM_DSMLv2_Login}</parameter>
<parameter name="jndiSearchBase">@PROPERTY{TIM_DSMLv2_SearchBase}</parameter>
</Configuration>
<Parser>
<InheritFrom>[parent]</InheritFrom>
</Parser>
<AttributeMap name="Input">
<InheritFrom>[parent]</InheritFrom>
</AttributeMap>
<AttributeMap name="Output">
<InheritFrom>[parent]</InheritFrom>
<AttributeMapItem>
<Name>displayName</Name>
<Type>simple</Type>
<Add>true</Add>
<Modify>true</Modify>
<Script/>
<Simple>cn</Simple>
</AttributeMapItem>
<AttributeMapItem>
<Name>erAliases</Name>
<Type>simple</Type>
<Add>true</Add>
<Modify>true</Modify>
<Script/>
<Simple>uid</Simple>
</AttributeMapItem>
<AttributeMapItem>
<Name>givenName</Name>
<Type>simple</Type>
<Add>true</Add>
<Modify>true</Modify>
<Script/>
<Simple>cn</Simple>
</AttributeMapItem>
</AttributeMap>
<DeltaSettings/>
<Schema>
<InheritFrom>[parent]</InheritFrom>
</Schema>
<LinkCriteria>
<InheritFrom>[parent]</InheritFrom>
<AdvancedLinkMode>false</AdvancedLinkMode>
</LinkCriteria>
<Hooks>
<InheritFrom>[parent]</InheritFrom>
<Hook>
<Name>default_fail</Name>
<Script>system.skipEntry();</Script>
<Enabled>true</Enabled>
<DebugBreak>false</DebugBreak>
</Hook>
</Hooks>
</Connector>
<Connector name="testout">
<InheritFrom>/Connectors/testout</InheritFrom>
<ConnectorMode>AddOnly</ConnectorMode>
<ConnectorState>Disabled</ConnectorState>
<Configuration>
<InheritFrom>[parent]</InheritFrom>
</Configuration>
<Parser>
<InheritFrom>[parent]</InheritFrom>
</Parser>
<AttributeMap name="Input">
<InheritFrom>[parent]</InheritFrom>
</AttributeMap>
<AttributeMap name="Output">
<InheritFrom>[parent]</InheritFrom>
<AttributeMapItem>
<Name>cn</Name>
<Type>simple</Type>
<Add>true</Add>
<Modify>true</Modify>
<Script/>
<Simple>cn</Simple>
</AttributeMapItem>
<AttributeMapItem>
<Name>secdn</Name>
<Type>simple</Type>
<Add>true</Add>
<Modify>true</Modify>
<Script/>
<Simple>secdn</Simple>
</AttributeMapItem>
<AttributeMapItem>
<Name>sn</Name>
<Type>simple</Type>
<Add>true</Add>
<Modify>true</Modify>
<Script/>
<Simple>sn</Simple>
</AttributeMapItem>
<AttributeMapItem>
<Name>uid</Name>
<Type>simple</Type>
<Add>true</Add>
<Modify>true</Modify>
<Script/>
<Simple>uid</Simple>
</AttributeMapItem>
</AttributeMap>
<DeltaSettings/>
<Schema>
<InheritFrom>[parent]</InheritFrom>
</Schema>
<LinkCriteria>
<InheritFrom>[parent]</InheritFrom>
<AdvancedLinkMode>false</AdvancedLinkMode>
</LinkCriteria>
<Hooks>
<InheritFrom>[parent]</InheritFrom>
</Hooks>
</Connector>
</Connectors>
</AssemblyLine>
</Folder>
<Folder name="Connectors">
<Connector name="FindMDLDAPTAMusers">
<InheritFrom>system:/Connectors/ibmdi.LDAP</InheritFrom>
<ConnectorMode>Iterator</ConnectorMode>
<ConnectorState>Enabled</ConnectorState>
<Configuration>
<InheritFrom>[parent]</InheritFrom>
<parameter name="automapADPassword">false</parameter>
<parameter name="debug">false</parameter>
<parameter name="ldapAuthenticationMethod">Simple</parameter>
<parameter name="ldapPageSize">0</parameter>
<parameter name="ldapPassword">secret</parameter>
<parameter name="ldapReferrals">follow</parameter>
<parameter name="ldapSearchBase">cn=Subdomains,secauthority=default</parameter>
<parameter name="ldapSearchFilter">objectClass=secMap</parameter>
<parameter name="ldapSearchScope">subtree</parameter>
<parameter name="ldapSizeLimit">0</parameter>
<parameter name="ldapTimeLimit">0</parameter>
<parameter name="ldapUrl">ldap://ender:389</parameter>
<parameter name="ldapUseSSL">false</parameter>
<parameter name="ldapUsername">cn=root</parameter>
<parameter name="ldapVLVPageSize">0</parameter>
<parameter name="simulateRename">true</parameter>
<parameter name="userComment"/>
</Configuration>
<Parser>
<InheritFrom>[parent]</InheritFrom>
</Parser>
<AttributeMap name="Input">
<InheritFrom>[parent]</InheritFrom>
</AttributeMap>
<AttributeMap name="Output">
<InheritFrom>[parent]</InheritFrom>
</AttributeMap>
<DeltaSettings/>
<Schema>
<InheritFrom>[parent]</InheritFrom>
<SchemaItem>
<Name>$dn</Name>
<Syntax>java.lang.String</Syntax>
<DefaultValue>null</DefaultValue>
<Syntax>java.lang.String</Syntax>
<RequiredInput>false</RequiredInput>
<RequiredOutput>false</RequiredOutput>
<Excluded>false</Excluded>
</SchemaItem>
<SchemaItem>
<Name>objectclass</Name>
<Syntax>java.lang.String</Syntax>
<DefaultValue>null</DefaultValue>
<Syntax>java.lang.String</Syntax>
<RequiredInput>false</RequiredInput>
<RequiredOutput>false</RequiredOutput>
<Excluded>false</Excluded>
</SchemaItem>
<SchemaItem>
<Name>secdn</Name>
<Syntax>java.lang.String</Syntax>
<DefaultValue>null</DefaultValue>
<Syntax>java.lang.String</Syntax>
<RequiredInput>false</RequiredInput>
<RequiredOutput>false</RequiredOutput>
<Excluded>false</Excluded>
</SchemaItem>
<SchemaItem>
<Name>secuuid</Name>
<Syntax>java.lang.String</Syntax>
<DefaultValue>null</DefaultValue>
<Syntax>java.lang.String</Syntax>
<RequiredInput>false</RequiredInput>
<RequiredOutput>false</RequiredOutput>
<Excluded>false</Excluded>
</SchemaItem>
</Schema>
<LinkCriteria>
<InheritFrom>[parent]</InheritFrom>
<AdvancedLinkMode>false</AdvancedLinkMode>
</LinkCriteria>
<Hooks>
<InheritFrom>[parent]</InheritFrom>
<Hook>
<Name>after_getnext</Name>
<Script><![CDATA[var tdn=conn.getString("$dn");
var sdn=conn.getString("secdn");
if ((tdn.indexOf("cn=users",0) <= 0)||(sdn.indexOf("SecurityMaster",0) > 0))
   system.skipEntry();
else
   task.logmsg("---> TAM user is found." + sdn);]]></Script>
<Enabled>true</Enabled>
<DebugBreak>false</DebugBreak>
</Hook>
<Hook>
<Name>default_fail</Name>
<Script>system.skipEntry();</Script>
<Enabled>true</Enabled>
<DebugBreak>false</DebugBreak>
</Hook>
</Hooks>
</Connector>
<Connector name="testout">
<InheritFrom>system:/Connectors/ibmdi.FileSystem</InheritFrom>
<ConnectorMode>AddOnly</ConnectorMode>
<ConnectorState>Enabled</ConnectorState>
<Configuration>
<InheritFrom>[parent]</InheritFrom>
<parameter name="debug">false</parameter>
<parameter name="fileAppend">false</parameter>
<parameter name="filePath">testout.dsml</parameter>
</Configuration>
<Parser>
<InheritFrom>system:/Parsers/ibmdi.DSML</InheritFrom>
<parameter name="dnattribute">$dn</parameter>
<parameter name="isnamespaceaware">false</parameter>
<parameter name="isvalidating">false</parameter>
<parameter name="omitxmldeclaration">false</parameter>
</Parser>
<AttributeMap name="Input">
<InheritFrom>[parent]</InheritFrom>
</AttributeMap>
<AttributeMap name="Output">
<InheritFrom>[parent]</InheritFrom>
</AttributeMap>
<DeltaSettings>
<InheritFrom>[no inheritance]</InheritFrom>
</DeltaSettings>
<Schema>
<InheritFrom>[parent]</InheritFrom>
</Schema>
<LinkCriteria>
<InheritFrom>[parent]</InheritFrom>
<AdvancedLinkMode>false</AdvancedLinkMode>
</LinkCriteria>
<Hooks>
<InheritFrom>[parent]</InheritFrom>
</Hooks>
</Connector>
<Connector name="GetMDLDAPTAMUsers">
<InheritFrom>system:/Connectors/ibmdi.LDAP</InheritFrom>
<ConnectorMode>Lookup</ConnectorMode>
<ConnectorState>Enabled</ConnectorState>
<Configuration>
<InheritFrom>[parent]</InheritFrom>
<parameter name="automapADPassword">false</parameter>
<parameter name="debug">false</parameter>
<parameter name="ldapAuthenticationMethod">Simple</parameter>
<parameter name="ldapPageSize">0</parameter>
<parameter name="ldapPassword">secret</parameter>
<parameter name="ldapReferrals">follow</parameter>
<parameter name="ldapSearchBase">ou=tivoli</parameter>
<parameter name="ldapSearchFilter">objectclass=person</parameter>
<parameter name="ldapSearchScope">subtree</parameter>
<parameter name="ldapSizeLimit">0</parameter>
<parameter name="ldapTimeLimit">0</parameter>
<parameter name="ldapUrl">ldap://ender:389</parameter>
<parameter name="ldapUseSSL">false</parameter>
<parameter name="ldapUsername">cn=root</parameter>
<parameter name="ldapVLVPageSize">0</parameter>
<parameter name="simulateRename">true</parameter>
<parameter name="userComment"/>
</Configuration>
<Parser>
<InheritFrom>[parent]</InheritFrom>
</Parser>
<AttributeMap name="Input">
<InheritFrom>[parent]</InheritFrom>
<AttributeMapItem>
<Name>cn</Name>
<Type>simple</Type>
<Add>true</Add>
<Modify>true</Modify>
<Script/>
<Simple>cn</Simple>
</AttributeMapItem>
<AttributeMapItem>
<Name>sn</Name>
<Type>simple</Type>
<Add>true</Add>
<Modify>true</Modify>
<Script/>
<Simple>sn</Simple>
</AttributeMapItem>
<AttributeMapItem>
<Name>uid</Name>
<Type>simple</Type>
<Add>true</Add>
<Modify>true</Modify>
<Script/>
<Simple>uid</Simple>
</AttributeMapItem>
</AttributeMap>
<AttributeMap name="Output">
<InheritFrom>[parent]</InheritFrom>
</AttributeMap>
<DeltaSettings/>
<Schema>
<InheritFrom>[parent]</InheritFrom>
<SchemaItem>
<Name>$dn</Name>
<Syntax>java.lang.String</Syntax>
<DefaultValue>null</DefaultValue>
<Syntax>java.lang.String</Syntax>
<RequiredInput>false</RequiredInput>
<RequiredOutput>false</RequiredOutput>
<Excluded>false</Excluded>
</SchemaItem>
<SchemaItem>
<Name>accessHint</Name>
<NativeSyntax>MAY/DN/DN pointer to an accessRole or accessGroup.</NativeSyntax>
<DefaultValue>null</DefaultValue>
<RequiredInput>false</RequiredInput>
<RequiredOutput>false</RequiredOutput>
<Excluded>false</Excluded>
</SchemaItem>
<SchemaItem>
<Name>accountHint</Name>
<NativeSyntax>MAY/DN/DN pointer to an account directory object.</NativeSyntax>
<DefaultValue>null</DefaultValue>
<RequiredInput>false</RequiredInput>
<RequiredOutput>false</RequiredOutput>
<Excluded>false</Excluded>
</SchemaItem>
<SchemaItem>
<Name>audio</Name>
<NativeSyntax>MAY/Binary/Contains a sound file in binary format.</NativeSyntax>
<DefaultValue>null</DefaultValue>
<RequiredInput>false</RequiredInput>
<RequiredOutput>false</RequiredOutput>
<Excluded>false</Excluded>
</SchemaItem>
<SchemaItem>
<Name>businessCategory</Name>
<NativeSyntax>MAY/Directory String/This attribute describes the kind of business performed by an organization.</NativeSyntax>
<DefaultValue>null</DefaultValue>
<RequiredInput>false</RequiredInput>
<RequiredOutput>false</RequiredOutput>
<Excluded>false</Excluded>
</SchemaItem>
<SchemaItem>
<Name>c</Name>
<NativeSyntax>MAY/String/This attribute contains a two-letter ISO 3166 country code (countryName).</NativeSyntax>
<DefaultValue>null</DefaultValue>
<RequiredInput>false</RequiredInput>
<RequiredOutput>false</RequiredOutput>
<Excluded>false</Excluded>
</SchemaItem>
<SchemaItem>
<Name>carLicense</Name>
<NativeSyntax>MAY/Directory String/vehicle license plate tag</NativeSyntax>
<DefaultValue>null</DefaultValue>
<RequiredInput>false</RequiredInput>
<RequiredOutput>false</RequiredOutput>
<Excluded>false</Excluded>
</SchemaItem>
<SchemaItem>
<Name>cn</Name>
<Syntax>java.lang.String</Syntax>
<NativeSyntax>MUST/String/This is the X.500 commonName attribute, which contains a name of an object.  If the object corresponds to a person, it is typically the persons full name.</NativeSyntax>
<DefaultValue>null</DefaultValue>
<Syntax>java.lang.String</Syntax>
<RequiredInput>false</RequiredInput>
<RequiredOutput>false</RequiredOutput>
<Excluded>false</Excluded>
</SchemaItem>
<SchemaItem>
<Name>configPtr</Name>
<NativeSyntax>MAY/DN/DN pointer to a cimConfiguration-derived directory entry such as an ePropertySet.</NativeSyntax>
<DefaultValue>null</DefaultValue>
<RequiredInput>false</RequiredInput>
<RequiredOutput>false</RequiredOutput>
<Excluded>false</Excluded>
</SchemaItem>
<SchemaItem>
<Name>departmentNumber</Name>
<NativeSyntax>MAY/Directory String/identifies a department within an organization.</NativeSyntax>
<DefaultValue>null</DefaultValue>
<RequiredInput>false</RequiredInput>
<RequiredOutput>false</RequiredOutput>
<Excluded>false</Excluded>
</SchemaItem>
<SchemaItem>
<Name>description</Name>
<NativeSyntax>MAY/Directory String/Attribute common to CIM and LDAP schema to provide lengthy description of a directory object entry.</NativeSyntax>
<DefaultValue>null</DefaultValue>
<RequiredInput>false</RequiredInput>
<RequiredOutput>false</RequiredOutput>
<Excluded>false</Excluded>
</SchemaItem>
<SchemaItem>
<Name>destinationIndicator</Name>
<NativeSyntax>MAY/Directory String/This attribute is used for the telegram service.</NativeSyntax>
<DefaultValue>null</DefaultValue>
<RequiredInput>false</RequiredInput>
<RequiredOutput>false</RequiredOutput>
<Excluded>false</Excluded>
</SchemaItem>
<SchemaItem>
<Name>displayName</Name>
<NativeSyntax>MAY/Directory String/A name used in displaying an entry in a one-line summary list.</NativeSyntax>
<DefaultValue>null</DefaultValue>
<RequiredInput>false</RequiredInput>
<RequiredOutput>false</RequiredOutput>
<Excluded>false</Excluded>
</SchemaItem>
<SchemaItem>
<Name>employeeNumber</Name>
<NativeSyntax>MAY/Directory String/Identifies the entrys employee number.</NativeSyntax>
<DefaultValue>null</DefaultValue>
<RequiredInput>false</RequiredInput>
<RequiredOutput>false</RequiredOutput>
<Excluded>false</Excluded>
</SchemaItem>
<SchemaItem>
<Name>employeeType</Name>
<NativeSyntax>MAY/Directory String/Identifies the entrys type of employment.</NativeSyntax>
<DefaultValue>null</DefaultValue>
<RequiredInput>false</RequiredInput>
<RequiredOutput>false</RequiredOutput>
<Excluded>false</Excluded>
</SchemaItem>
<SchemaItem>
<Name>facsimileTelephoneNumber</Name>
<NativeSyntax>MAY/Telephone Number/Identifies the fax number at which the entry can be reached.</NativeSyntax>
<DefaultValue>null</DefaultValue>
<RequiredInput>false</RequiredInput>
<RequiredOutput>false</RequiredOutput>
<Excluded>false</Excluded>
</SchemaItem>
<SchemaItem>
<Name>generationQualifier</Name>
<NativeSyntax>MAY/String/Contains the part of the name which typically is the suffix, as in IIIrd.</NativeSyntax>
<DefaultValue>null</DefaultValue>
<RequiredInput>false</RequiredInput>
<RequiredOutput>false</RequiredOutput>
<Excluded>false</Excluded>
</SchemaItem>
<SchemaItem>
<Name>givenName</Name>
<NativeSyntax>MAY/String/Used to hold the part of a persons name which is not their surname nor middle name.</NativeSyntax>
<DefaultValue>null</DefaultValue>
<RequiredInput>false</RequiredInput>
<RequiredOutput>false</RequiredOutput>
<Excluded>false</Excluded>
</SchemaItem>
<SchemaItem>
<Name>homeFax</Name>
<NativeSyntax>MAY/Telephone Number/Identifies the entrys home fax number.</NativeSyntax>
<DefaultValue>null</DefaultValue>
<RequiredInput>false</RequiredInput>
<RequiredOutput>false</RequiredOutput>
<Excluded>false</Excluded>
</SchemaItem>
<SchemaItem>
<Name>homePhone</Name>
<NativeSyntax>MAY/Telephone Number/Identifies the entrys home phone number.</NativeSyntax>
<DefaultValue>null</DefaultValue>
<RequiredInput>false</RequiredInput>
<RequiredOutput>false</RequiredOutput>
<Excluded>false</Excluded>
</SchemaItem>
<SchemaItem>
<Name>homePostalAddress</Name>
<NativeSyntax>MAY/Directory String/Identifies the entrys home mailing address. This field is  intended to include multiple lines, but each line within the  entry should be separated by a dollar sign (\24). To represent  an actual dollar sign (\24) or backslash (\) within this text, use  the escaped hex values \24 and \5c respectively.</NativeSyntax>
<DefaultValue>null</DefaultValue>
<RequiredInput>false</RequiredInput>
<RequiredOutput>false</RequiredOutput>
<Excluded>false</Excluded>
</SchemaItem>
<SchemaItem>
<Name>initials</Name>
<NativeSyntax>MAY/String/The initials attribute contains the initials of some or all of an individuals names, but not the surname(s).</NativeSyntax>
<DefaultValue>null</DefaultValue>
<RequiredInput>false</RequiredInput>
<RequiredOutput>false</RequiredOutput>
<Excluded>false</Excluded>
</SchemaItem>
<SchemaItem>
<Name>internationalISDNNumber</Name>
<NativeSyntax>MAY/IA5 String/Contains the ISDN number of the entry. This is in the internationally agreed format for ISDN addresses given in CCITT Rec. E. 164.</NativeSyntax>
<DefaultValue>null</DefaultValue>
<RequiredInput>false</RequiredInput>
<RequiredOutput>false</RequiredOutput>
<Excluded>false</Excluded>
</SchemaItem>
<SchemaItem>
<Name>jpegPhoto</Name>
<NativeSyntax>MAY/Binary/Contains a JPEG photo of the entry.</NativeSyntax>
<DefaultValue>null</DefaultValue>
<RequiredInput>false</RequiredInput>
<RequiredOutput>false</RequiredOutput>
<Excluded>false</Excluded>
</SchemaItem>
<SchemaItem>
<Name>l</Name>
<NativeSyntax>MAY/String/This attribute contains the name of a locality, such as a city, county or other geographic region (localityName).</NativeSyntax>
<DefaultValue>null</DefaultValue>
<RequiredInput>false</RequiredInput>
<RequiredOutput>false</RequiredOutput>
<Excluded>false</Excluded>
</SchemaItem>
<SchemaItem>
<Name>labeledURI</Name>
<NativeSyntax>MAY/Directory String/Uniform Resource Identifier with optional label as defined in RFC2079.</NativeSyntax>
<DefaultValue>null</DefaultValue>
<RequiredInput>false</RequiredInput>
<RequiredOutput>false</RequiredOutput>
<Excluded>false</Excluded>
</SchemaItem>
<SchemaItem>
<Name>mail</Name>
<NativeSyntax>MAY/Directory String/Identifies a users primary email address (the email address retrieved and displayed by white-pages lookup applications).</NativeSyntax>
<DefaultValue>null</DefaultValue>
<RequiredInput>false</RequiredInput>
<RequiredOutput>false</RequiredOutput>
<Excluded>false</Excluded>
</SchemaItem>
<SchemaItem>
<Name>manager</Name>
<NativeSyntax>MAY/DN/Identifies the distinguished name of the entrys manager.</NativeSyntax>
<DefaultValue>null</DefaultValue>
<RequiredInput>false</RequiredInput>
<RequiredOutput>false</RequiredOutput>
<Excluded>false</Excluded>
</SchemaItem>
<SchemaItem>
<Name>middleName</Name>
<NativeSyntax>MAY/String/Identifies the entrys middle name.</NativeSyntax>
<DefaultValue>null</DefaultValue>
<RequiredInput>false</RequiredInput>
<RequiredOutput>false</RequiredOutput>
<Excluded>false</Excluded>
</SchemaItem>
<SchemaItem>
<Name>mobile</Name>
<NativeSyntax>MAY/Telephone Number/Identifies the entrys mobile or cellular phone number.</NativeSyntax>
<DefaultValue>null</DefaultValue>
<RequiredInput>false</RequiredInput>
<RequiredOutput>false</RequiredOutput>
<Excluded>false</Excluded>
</SchemaItem>
<SchemaItem>
<Name>o</Name>
<NativeSyntax>MAY/String/This attribute contains the name of an organization (organizationName).</NativeSyntax>
<DefaultValue>null</DefaultValue>
<RequiredInput>false</RequiredInput>
<RequiredOutput>false</RequiredOutput>
<Excluded>false</Excluded>
</SchemaItem>
<SchemaItem>
<Name>objectClass</Name>
<NativeSyntax>MUST/OID/The values of the objectClass attribute describe the kind of object which an entry represents.</NativeSyntax>
<DefaultValue>null</DefaultValue>
<RequiredInput>false</RequiredInput>
<RequiredOutput>false</RequiredOutput>
<Excluded>false</Excluded>
</SchemaItem>
<SchemaItem>
<Name>objectclass</Name>
<Syntax>java.lang.String</Syntax>
<DefaultValue>null</DefaultValue>
<Syntax>java.lang.String</Syntax>
<RequiredInput>false</RequiredInput>
<RequiredOutput>false</RequiredOutput>
<Excluded>false</Excluded>
</SchemaItem>
<SchemaItem>
<Name>organizationalStatus</Name>
<NativeSyntax>MAY/Directory String/Specifies a category by which a person is often referred to in an organization.</NativeSyntax>
<DefaultValue>null</DefaultValue>
<RequiredInput>false</RequiredInput>
<RequiredOutput>false</RequiredOutput>
<Excluded>false</Excluded>
</SchemaItem>
<SchemaItem>
<Name>otherMailbox</Name>
<NativeSyntax>MAY/Directory String/Specifies values for electronic mailbox types other than X.400 and rfc822.</NativeSyntax>
<DefaultValue>null</DefaultValue>
<RequiredInput>false</RequiredInput>
<RequiredOutput>false</RequiredOutput>
<Excluded>false</Excluded>
</SchemaItem>
<SchemaItem>
<Name>ou</Name>
<NativeSyntax>MAY/String/This attribute contains the name of an organization (organizationName).</NativeSyntax>
<DefaultValue>null</DefaultValue>
<RequiredInput>false</RequiredInput>
<RequiredOutput>false</RequiredOutput>
<Excluded>false</Excluded>
</SchemaItem>
<SchemaItem>
<Name>pager</Name>
<NativeSyntax>MAY/Telephone Number/Identifies the entrys pager phone number.</NativeSyntax>
<DefaultValue>null</DefaultValue>
<RequiredInput>false</RequiredInput>
<RequiredOutput>false</RequiredOutput>
<Excluded>false</Excluded>
</SchemaItem>
<SchemaItem>
<Name>personalTitle</Name>
<NativeSyntax>MAY/Directory String/Specifies a personal title for a person. Examples of personal titles are  Mr, Ms, Dr, Prof and Rev.</NativeSyntax>
<DefaultValue>null</DefaultValue>
<RequiredInput>false</RequiredInput>
<RequiredOutput>false</RequiredOutput>
<Excluded>false</Excluded>
</SchemaItem>
<SchemaItem>
<Name>photo</Name>
<NativeSyntax>MAY/Binary/Contains a photo, in binary form, of the entry.</NativeSyntax>
<DefaultValue>null</DefaultValue>
<RequiredInput>false</RequiredInput>
<RequiredOutput>false</RequiredOutput>
<Excluded>false</Excluded>
</SchemaItem>
<SchemaItem>
<Name>physicalDeliveryOfficeName</Name>
<NativeSyntax>MAY/Directory String/Physcial delivery office number.</NativeSyntax>
<DefaultValue>null</DefaultValue>
<RequiredInput>false</RequiredInput>
<RequiredOutput>false</RequiredOutput>
<Excluded>false</Excluded>
</SchemaItem>
<SchemaItem>
<Name>postOfficeBox</Name>
<NativeSyntax>MAY/Directory String/Post office box number.</NativeSyntax>
<DefaultValue>null</DefaultValue>
<RequiredInput>false</RequiredInput>
<RequiredOutput>false</RequiredOutput>
<Excluded>false</Excluded>
</SchemaItem>
<SchemaItem>
<Name>postalAddress</Name>
<NativeSyntax>MAY/Directory String/Identifies the entry\27s mailing address. This field is intended to include multiple lines. When represented in LDIF format, each line should be separated by a dollar sign (\24).</NativeSyntax>
<DefaultValue>null</DefaultValue>
<RequiredInput>false</RequiredInput>
<RequiredOutput>false</RequiredOutput>
<Excluded>false</Excluded>
</SchemaItem>
<SchemaItem>
<Name>postalCode</Name>
<NativeSyntax>MAY/Directory String/Postal code.</NativeSyntax>
<DefaultValue>null</DefaultValue>
<RequiredInput>false</RequiredInput>
<RequiredOutput>false</RequiredOutput>
<Excluded>false</Excluded>
</SchemaItem>
<SchemaItem>
<Name>preferredDeliveryMethod</Name>
<NativeSyntax>MAY/Directory String/Identifies the entry\27s preferred contact or delivery method.</NativeSyntax>
<DefaultValue>null</DefaultValue>
<RequiredInput>false</RequiredInput>
<RequiredOutput>false</RequiredOutput>
<Excluded>false</Excluded>
</SchemaItem>
<SchemaItem>
<Name>preferredLanguage</Name>
<NativeSyntax>MAY/Directory String/A persons preferred written or spoken language</NativeSyntax>
<DefaultValue>null</DefaultValue>
<RequiredInput>false</RequiredInput>
<RequiredOutput>false</RequiredOutput>
<Excluded>false</Excluded>
</SchemaItem>
<SchemaItem>
<Name>registeredAddress</Name>
<NativeSyntax>MAY/String/This attribute contains a postal address for receiving telegrams or expedited documents. The recipient\27s signature is usually required on delivery.</NativeSyntax>
<DefaultValue>null</DefaultValue>
<RequiredInput>false</RequiredInput>
<RequiredOutput>false</RequiredOutput>
<Excluded>false</Excluded>
</SchemaItem>
<SchemaItem>
<Name>roomNumber</Name>
<NativeSyntax>MAY/Directory String/Specifies the room number of an object. Note that the commonName attribute should be used for naming room  objects.</NativeSyntax>
<DefaultValue>null</DefaultValue>
<RequiredInput>false</RequiredInput>
<RequiredOutput>false</RequiredOutput>
<Excluded>false</Excluded>
</SchemaItem>
<SchemaItem>
<Name>secretary</Name>
<NativeSyntax>MAY/DN/Identifies the entrys secretary or administrative assistant.</NativeSyntax>
<DefaultValue>null</DefaultValue>
<RequiredInput>false</RequiredInput>
<RequiredOutput>false</RequiredOutput>
<Excluded>false</Excluded>
</SchemaItem>
<SchemaItem>
<Name>seeAlso</Name>
<NativeSyntax>MAY/String/Identifies another directory server entry that may contain information related to this entry.</NativeSyntax>
<DefaultValue>null</DefaultValue>
<RequiredInput>false</RequiredInput>
<RequiredOutput>false</RequiredOutput>
<Excluded>false</Excluded>
</SchemaItem>
<SchemaItem>
<Name>sn</Name>
<Syntax>java.lang.String</Syntax>
<NativeSyntax>MUST/String/This is the X.500 surname attribute, which contains the family name of a person.</NativeSyntax>
<DefaultValue>null</DefaultValue>
<Syntax>java.lang.String</Syntax>
<RequiredInput>false</RequiredInput>
<RequiredOutput>false</RequiredOutput>
<Excluded>false</Excluded>
</SchemaItem>
<SchemaItem>
<Name>st</Name>
<NativeSyntax>MAY/String/This attribute contains the full name of a state or province (stateOrProvinceName).</NativeSyntax>
<DefaultValue>null</DefaultValue>
<RequiredInput>false</RequiredInput>
<RequiredOutput>false</RequiredOutput>
<Excluded>false</Excluded>
</SchemaItem>
<SchemaItem>
<Name>street</Name>
<NativeSyntax>MAY/Directory String/This attribute contains the physical address of the object to which the entry corresponds, such as an address for package delivery (streetAddress).</NativeSyntax>
<DefaultValue>null</DefaultValue>
<RequiredInput>false</RequiredInput>
<RequiredOutput>false</RequiredOutput>
<Excluded>false</Excluded>
</SchemaItem>
<SchemaItem>
<Name>telephoneNumber</Name>
<NativeSyntax>MAY/Telephone Number/Telephone number.</NativeSyntax>
<DefaultValue>null</DefaultValue>
<RequiredInput>false</RequiredInput>
<RequiredOutput>false</RequiredOutput>
<Excluded>false</Excluded>
</SchemaItem>
<SchemaItem>
<Name>teletexTerminalIdentifier</Name>
<NativeSyntax>MAY/Directory String/Teletex terminal identifier.</NativeSyntax>
<DefaultValue>null</DefaultValue>
<RequiredInput>false</RequiredInput>
<RequiredOutput>false</RequiredOutput>
<Excluded>false</Excluded>
</SchemaItem>
<SchemaItem>
<Name>telexNumber</Name>
<NativeSyntax>MAY/Directory String/Telex number.</NativeSyntax>
<DefaultValue>null</DefaultValue>
<RequiredInput>false</RequiredInput>
<RequiredOutput>false</RequiredOutput>
<Excluded>false</Excluded>
</SchemaItem>
<SchemaItem>
<Name>thumbNailLogo</Name>
<NativeSyntax>MAY/Binary/Thumbnail logo assoicated with a user.</NativeSyntax>
<DefaultValue>null</DefaultValue>
<RequiredInput>false</RequiredInput>
<RequiredOutput>false</RequiredOutput>
<Excluded>false</Excluded>
</SchemaItem>
<SchemaItem>
<Name>thumbNailPhoto</Name>
<NativeSyntax>MAY/Binary/Thumbnail photo associated with a user.</NativeSyntax>
<DefaultValue>null</DefaultValue>
<RequiredInput>false</RequiredInput>
<RequiredOutput>false</RequiredOutput>
<Excluded>false</Excluded>
</SchemaItem>
<SchemaItem>
<Name>title</Name>
<NativeSyntax>MAY/String/This attribute contains the title, such as Vice President, of a person in their organizational context. The personalTitle attribute would be used for a persons title independent of their job function.</NativeSyntax>
<DefaultValue>null</DefaultValue>
<RequiredInput>false</RequiredInput>
<RequiredOutput>false</RequiredOutput>
<Excluded>false</Excluded>
</SchemaItem>
<SchemaItem>
<Name>uid</Name>
<Syntax>java.lang.String</Syntax>
<NativeSyntax>MAY/Directory String/Typically a user shortname or userid.</NativeSyntax>
<DefaultValue>null</DefaultValue>
<Syntax>java.lang.String</Syntax>
<RequiredInput>false</RequiredInput>
<RequiredOutput>false</RequiredOutput>
<Excluded>false</Excluded>
</SchemaItem>
<SchemaItem>
<Name>uniqueIdentifier</Name>
<NativeSyntax>MAY/Directory String/Specifies a unique identifier for an object represented in the Directory. The domain within which the identifier is unique, and the exact semantics of the identifier, are for local definition.</NativeSyntax>
<DefaultValue>null</DefaultValue>
<RequiredInput>false</RequiredInput>
<RequiredOutput>false</RequiredOutput>
<Excluded>false</Excluded>
</SchemaItem>
<SchemaItem>
<Name>userCertificate</Name>
<NativeSyntax>MAY/Binary/Used to represent certificates from one or more Certification Authorities representing a user.</NativeSyntax>
<DefaultValue>null</DefaultValue>
<RequiredInput>false</RequiredInput>
<RequiredOutput>false</RequiredOutput>
<Excluded>false</Excluded>
</SchemaItem>
<SchemaItem>
<Name>userPKCS12</Name>
<NativeSyntax>MAY/Binary/PKCS \2312 PFX PDU for exchange of personal identity information</NativeSyntax>
<DefaultValue>null</DefaultValue>
<RequiredInput>false</RequiredInput>
<RequiredOutput>false</RequiredOutput>
<Excluded>false</Excluded>
</SchemaItem>
<SchemaItem>
<Name>userPassword</Name>
<NativeSyntax>MAY/Binary/Holds a password value for a distinguished name.</NativeSyntax>
<DefaultValue>null</DefaultValue>
<RequiredInput>false</RequiredInput>
<RequiredOutput>false</RequiredOutput>
<Excluded>false</Excluded>
</SchemaItem>
<SchemaItem>
<Name>userSMIMECertificate</Name>
<NativeSyntax>MAY/Binary/Signed message used to support S/MIME</NativeSyntax>
<DefaultValue>null</DefaultValue>
<RequiredInput>false</RequiredInput>
<RequiredOutput>false</RequiredOutput>
<Excluded>false</Excluded>
</SchemaItem>
<SchemaItem>
<Name>userpassword</Name>
<Syntax>[byte array]</Syntax>
<DefaultValue>null</DefaultValue>
<Syntax>[byte array]</Syntax>
<RequiredInput>false</RequiredInput>
<RequiredOutput>false</RequiredOutput>
<Excluded>false</Excluded>
</SchemaItem>
<SchemaItem>
<Name>x121Address</Name>
<NativeSyntax>MAY/IA5 String/Defines the X.121 address of the entry.</NativeSyntax>
<DefaultValue>null</DefaultValue>
<RequiredInput>false</RequiredInput>
<RequiredOutput>false</RequiredOutput>
<Excluded>false</Excluded>
</SchemaItem>
<SchemaItem>
<Name>x500UniqueIdentifier</Name>
<NativeSyntax>MAY/Binary/Used to distinguish between objects when a distinguished name has been reused. This is a different attribute type from both the uid and uniqueIdentifier types.</NativeSyntax>
<DefaultValue>null</DefaultValue>
<RequiredInput>false</RequiredInput>
<RequiredOutput>false</RequiredOutput>
<Excluded>false</Excluded>
</SchemaItem>
</Schema>
<LinkCriteria>
<InheritFrom>[parent]</InheritFrom>
<AdvancedLinkMode>false</AdvancedLinkMode>
</LinkCriteria>
<Hooks>
<InheritFrom>[parent]</InheritFrom>
<Hook>
<Name>default_fail</Name>
<Script>system.skipEntry();</Script>
<Enabled>true</Enabled>
<DebugBreak>false</DebugBreak>
</Hook>
</Hooks>
</Connector>
<Connector name="TIMImport">
<InheritFrom>system:/Connectors/ibmdi.JNDI</InheritFrom>
<ConnectorMode>AddOnly</ConnectorMode>
<ConnectorState>Enabled</ConnectorState>
<Configuration>
<InheritFrom>[parent]</InheritFrom>
<parameter name="debug">false</parameter>
<parameter name="java.naming.factory.initial">com.ibm.dsml2.jndi.DSML2InitialContextFactory</parameter>
<parameter name="java.naming.provider.url">http://hostname:9080/enrole/dsml2_event_handler/tivoli</parameter>
<parameter name="java.naming.referral">follow</parameter>
<parameter name="java.naming.security.authentication">Simple</parameter>
<parameter name="java.naming.security.credentials">agent</parameter>
<parameter name="java.naming.security.principal">agent</parameter>
<parameter name="jndiSearchBase">dc=HRLoad</parameter>
<parameter name="jndiSearchFilter">(objectclass=*)</parameter>
<parameter name="jndiSearchScope">subtree</parameter>
</Configuration>
<Parser>
<InheritFrom>[parent]</InheritFrom>
</Parser>
<AttributeMap name="Input">
<InheritFrom>[parent]</InheritFrom>
</AttributeMap>
<AttributeMap name="Output">
<InheritFrom>[parent]</InheritFrom>
<AttributeMapItem>
<Name>$dn</Name>
<Type>advanced</Type>
<Add>true</Add>
<Modify>true</Modify>
<Script>ret.value = "uid=" + work.getString("uid") + "," + TIMImport.getConnectorParam("jndiSearchBase");</Script>
<Simple>$dn</Simple>
</AttributeMapItem>
<AttributeMapItem>
<Name>cn</Name>
<Type>simple</Type>
<Add>true</Add>
<Modify>true</Modify>
<Script/>
<Simple>cn</Simple>
</AttributeMapItem>
<AttributeMapItem>
<Name>displayName</Name>
<Type>simple</Type>
<Add>true</Add>
<Modify>true</Modify>
<Script/>
<Simple>displayName</Simple>
</AttributeMapItem>
<AttributeMapItem>
<Name>erAliases</Name>
<Type>simple</Type>
<Add>true</Add>
<Modify>true</Modify>
<Script/>
<Simple>erAliases</Simple>
</AttributeMapItem>
<AttributeMapItem>
<Name>givenName</Name>
<Type>simple</Type>
<Add>true</Add>
<Modify>true</Modify>
<Script/>
<Simple>givenName</Simple>
</AttributeMapItem>
<AttributeMapItem>
<Name>objectclass</Name>
<Type>advanced</Type>
<Add>true</Add>
<Modify>true</Modify>
<Script>ret.value="inetOrgPerson";</Script>
<Simple>objectclass</Simple>
</AttributeMapItem>
<AttributeMapItem>
<Name>sn</Name>
<Type>simple</Type>
<Add>true</Add>
<Modify>true</Modify>
<Script/>
<Simple>sn</Simple>
</AttributeMapItem>
<AttributeMapItem>
<Name>uid</Name>
<Type>simple</Type>
<Add>true</Add>
<Modify>true</Modify>
<Script/>
<Simple>uid</Simple>
</AttributeMapItem>
</AttributeMap>
<DeltaSettings/>
<Schema>
<InheritFrom>[parent]</InheritFrom>
</Schema>
<LinkCriteria>
<InheritFrom>[parent]</InheritFrom>
<AdvancedLinkMode>false</AdvancedLinkMode>
</LinkCriteria>
<Hooks>
<InheritFrom>[parent]</InheritFrom>
<Hook>
<Name>default_fail</Name>
<Script>system.skipEntry();</Script>
<Enabled>true</Enabled>
<DebugBreak>false</DebugBreak>
</Hook>
</Hooks>
</Connector>
</Folder>
<Folder name="Parsers"/>
<Folder name="EventHandlers"/>
<Folder name="Scripts"/>
<JavaLibraries/>
<JavaProperties/>
<Folder name="Includes"/>
<ExternalProperties>
<Path>C:\Program Files\ibm\IBMDirectoryIntegrator\TIMTAMIntegration\MDTAMtoTIMImport.properties</Path>
<Encrypted>false</Encrypted>
</ExternalProperties>
</MetamergeConfig>
